frictionless_geojson/__init__.py
tests/__init__.py
tests/conftest.py
tests/test_file.py
tests/test_geojson.py
tests/test_resource.py
frictionless_geojson-0.0.2.dist-info/LICENSE.md
frictionless_geojson-0.0.2.dist-info/METADATA
frictionless_geojson-0.0.2.dist-info/WHEEL
frictionless_geojson-0.0.2.dist-info/top_level.txt
frictionless_geojson-0.0.2.dist-info/RECORD
